[
  {
    "id": 1,
    "title": "Smartlock",
    "img": "assets/images/projects/placeholder.png",
    "url": "",
    "overview": "online",
    "technologies": [],
    "details": []
  },
  {
    "id": 2,
    "title": "Passport Smartforms",
    "img": "assets/images/projects/placeholder.png",
    "url": "",
    "overview": "online",
    "technologies": [],
    "details": []
  },
  {
    "id": 3,
    "title": "Python Blockchain",
    "img": "assets/images/projects/placeholder.png",
    "url": "",
    "overview": "online",
    "technologies": [],
    "details": []
  },
  {
    "id": 4,
    "title": "BDT-Template",
    "img": "assets/images/projects/bdt-cover.png",
    "url": "",
    "overview": "online",
    "technologies": [],
    "details": []
  },
  {
    "id": 5,
    "title": "Electron-Angular",
    "img": "assets/images/projects/electron.png",
    "url": "",
    "overview": "online",
    "technologies": [
      "angular", "cli", "electron", "jasmine", "karma",
      "protractor", "rxjs", "sass", "typescript"
    ],
    "details": []
  },
  {
    "id": 6,
    "title": "Forestry TEP",
    "img": "assets/images/projects/ftep-cover.png",
    "url": "https://f-tep.com/app/",
    "overview": "online",
    "technologies": [
      "angularjs", "bootstrap", "grunt", "hateoas", "jasmine",
      "karma", "less", "material", "openlayers"
    ],
    "details": []
  },
  {
    "id": 7,
    "title": "Kanban Board",
    "img": "assets/images/projects/kanban-cover.png",
    "url": "https://kanban.davidnorton.app/",
    "overview": "online",
    "technologies": [
      "angular", "bootstrap", "cli", "jasmine", "karma",
      "ng-bootstrap", "protractor", "rxjs", "sass", "typescript"
    ],
    "details": []
  },
  {
    "id": 8,
    "title": "Crypto Dashboard",
    "img": "assets/images/projects/crypto-cover.png",
    "url": "https://crypto.davidnorton.app/",
    "overview": "online",
    "technologies": [
      "angular", "bootstrap", "cli", "firebase", "jasmine", "karma",
      "ng-bootstrap", "protractor", "rxjs", "sass", "typescript"
    ],
    "details": []
  },
  {
    "id": 9,
    "title": "Cookbook",
    "img": "assets/images/projects/cookbook-cover.png",
    "url": "https://cookbook.davidnorton.app/",
    "overview": "online",
    "technologies": [
      "angular", "bootstrap", "cli", "firebase", "jasmine", "karma",
      "ng-bootstrap", "ngrx", "protractor", "rxjs", "sass", "typescript"
    ],
    "details": []
  },
  {
    "id": 10,
    "title": "Forestry TEP v3",
    "img": "assets/images/projects/ftepv3-cover.png",
    "url": "https://ftep.davidnorton.app/",
    "overview": "online",
    "technologies": [
      "angular", "bootstrap", "cli", "jasmine", "karma", "ng-bootstrap",
      "ngrx", "penv", "protractor", "rxjs", "sass", "travis", "typescript"
    ],
    "details": []
  },
  {
    "id": 11,
    "title": "Forefront",
    "img": "assets/images/projects/forefront-cover.png",
    "url": "https://forefront.davidnorton.app/",
    "overview": "Forefront is a template Angular 7 project",
    "technologies": [
      "angular", "chai", "cli", "compodoc", "cucumber", "cypress",
      "express", "jasmine", "karma", "kss", "lighthouse", "material",
      "mocha", "ngrx", "penv", "pwa", "rxjs", "sass", "typescript", "universal"
    ],
    "details": [

    ]
  }
]
